{"trial_id": "0085", "hyperparameters": {"space": [{"class_name": "Choice", "config": {"name": "activation", "default": "relu", "conditions": [], "values": ["relu", "tanh", "sigmoid"], "ordered": false}}, {"class_name": "Int", "config": {"name": "first_units", "default": null, "conditions": [], "min_value": 1, "max_value": 50, "step": 2, "sampling": "linear"}}, {"class_name": "Int", "config": {"name": "num_layers", "default": null, "conditions": [], "min_value": 1, "max_value": 12, "step": 1, "sampling": "linear"}}, {"class_name": "Int", "config": {"name": "units_0", "default": null, "conditions": [], "min_value": 1, "max_value": 81, "step": 2, "sampling": "linear"}}, {"class_name": "Int", "config": {"name": "units_1", "default": null, "conditions": [], "min_value": 1, "max_value": 81, "step": 2, "sampling": "linear"}}, {"class_name": "Int", "config": {"name": "units_2", "default": null, "conditions": [], "min_value": 1, "max_value": 81, "step": 2, "sampling": "linear"}}, {"class_name": "Int", "config": {"name": "units_3", "default": null, "conditions": [], "min_value": 1, "max_value": 81, "step": 2, "sampling": "linear"}}, {"class_name": "Int", "config": {"name": "units_4", "default": null, "conditions": [], "min_value": 1, "max_value": 81, "step": 2, "sampling": "linear"}}, {"class_name": "Int", "config": {"name": "units_5", "default": null, "conditions": [], "min_value": 1, "max_value": 81, "step": 2, "sampling": "linear"}}, {"class_name": "Int", "config": {"name": "units_6", "default": null, "conditions": [], "min_value": 1, "max_value": 81, "step": 2, "sampling": "linear"}}, {"class_name": "Int", "config": {"name": "units_7", "default": null, "conditions": [], "min_value": 1, "max_value": 81, "step": 2, "sampling": "linear"}}, {"class_name": "Int", "config": {"name": "units_8", "default": null, "conditions": [], "min_value": 1, "max_value": 81, "step": 2, "sampling": "linear"}}, {"class_name": "Int", "config": {"name": "units_9", "default": null, "conditions": [], "min_value": 1, "max_value": 81, "step": 2, "sampling": "linear"}}, {"class_name": "Int", "config": {"name": "units_10", "default": null, "conditions": [], "min_value": 1, "max_value": 81, "step": 2, "sampling": "linear"}}, {"class_name": "Int", "config": {"name": "units_11", "default": null, "conditions": [], "min_value": 1, "max_value": 81, "step": 2, "sampling": "linear"}}], "values": {"activation": "tanh", "first_units": 13, "num_layers": 2, "units_0": 79, "units_1": 35, "units_2": 17, "units_3": 3, "units_4": 47, "units_5": 59, "units_6": 21, "units_7": 31, "units_8": 31, "units_9": 73, "units_10": 27, "units_11": 53, "tuner/epochs": 30, "tuner/initial_epoch": 0, "tuner/bracket": 0, "tuner/round": 0}}, "metrics": {"metrics": {"accuracy": {"direction": "max", "observations": [{"value": [0.7321282625198364], "step": 9}]}, "loss": {"direction": "min", "observations": [{"value": [0.5472418069839478], "step": 9}]}, "val_accuracy": {"direction": "max", "observations": [{"value": [0.7364730834960938], "step": 9}]}, "val_loss": {"direction": "min", "observations": [{"value": [0.544287919998169], "step": 9}]}}}, "score": 0.7364730834960938, "best_step": 9, "status": "COMPLETED", "message": null}